<?xml version="1.0" ?>
<configuration>
	<datagrid>
		<element label="企业名称" field="name" width="100" />
		<element label="产业类别" field="type" width="100" />
		<element label="其它信息" field="info" width="100" />
	</datagrid>
	<datagridPopup>
		<element label="类别" field="name" width="120"/>
		<element label="内容" field="value" width="150"/>
		<element label="单位" field="unit" width="50" />
		</datagridPopup>
	<contents>
		<element label="年末总人口" field=""  unit="万人"/>
		<element label="其中：女" field=""   unit="万人"/>
		<element label="年末单位从业人员" field=""   unit="人"/>
		<element label="乡村从业人员" field=""   unit="人"/>
		<element label="地区生产总值" field=""   unit="万元"/>
		<element label="第一产业增加值" field=""   unit="万元"/>
		<element label="农业" field=""   unit="万元"/>
		<element label="林业" field=""   unit="万元"/>
		<element label="牧业" field=""   unit="万元"/>
		<element label="渔业" field=""  unit="万元"/>
		<element label="农林牧渔服务业" field=""   unit="万元"/>
<element label="第二产业增加值" field=""   unit="万元"/>
		<element label="工业" field=""   unit="万元"/>
		<element label="第三产业增加值" field=""   unit="万元"/>
		<element label="财政总收入" field=""   unit="万元"/>
		<element label="规模以上工业企业数" field=""  unit="个"/>
		<element label="工业总产值" field=""   unit="万元"/>
		<element label="星级饭店个数" field=""   unit="个"/>
		<element label="星级饭店客房总数" field=""   unit="间"/>
		<element label="自然保护区个数" field=""   unit="个"/>
		<element label="自然保护区面积" field=""   unit="公顷"/>
		<element label="污水处理厂数" field=""  unit="座"/>
		<element label="垃圾处理站数" field=""   unit="个"/>
		<element label="全社会用电量" field=""   unit="万千瓦时"/>
		<element label="其中：工业用电量" field=""   unit="万千瓦时"/>
		<element label="居民生活用电量" field=""   unit="万千瓦时"/>
		<element label="自来水受益村" field=""   unit="个"/>
	</contents>
	<popup>
		<element label="名称" field="name" />
		<element label="级别" field="value" />
		<element label="核准面积" field="value" />
		<element label="填海面积" field="value" />
		<element label="海岸线长度" field="value" />
		<element label="地区生产总值" field="value" />
		<element label="财政收入" field="value" />
		<element label="税收收入" field="value" />
		<element label="进口总额" field="value" />
		<element label="出口总额" field="value" />
		<element label="固定资产投资额" field="value" />
		<element label="年末从业人员" field="value" />
		<element label="单位数量" field="value" />
	</popup>
</configuration>
